biser/__init__.py
biser/__main__.py
biser/cover.py
biser/version.py
biser/exe/biser.exe
biser/exe/libcodonrt.so
biser/exe/libomp.so
biser-1.4.dist-info/LICENSE
biser-1.4.dist-info/METADATA
biser-1.4.dist-info/WHEEL
biser-1.4.dist-info/entry_points.txt
biser-1.4.dist-info/top_level.txt
biser-1.4.dist-info/RECORD
